[
  {
    "중개사_정보": {},
    "매물번호": "18306858",
    "매물_URL": "https://www.peterpanz.com/house/18306858",
    "매물_이미지": [
      "https://img.peterpanz.com/photo/20251025/18306858/6191eee5f6ba6d2f7ab43a5581c3919c_origin.jpg",
      "https://img.peterpanz.com/photo/20251025/18306858/66969e974b4fb77f821ffcea6d80055e_origin.jpg",
      "https://img.peterpanz.com/photo/20251025/18306858/13752d933282e5ce784ff4fb0b844699_origin.jpg",
      "https://img.peterpanz.com/photo/20251025/18306858/ca2f9edfc9c30294b4ef1ddeee17478a_origin.jpg",
      "https://img.peterpanz.com/photo/20251025/18306858/f6b4c64b760313435f3d6b80848f03dc_origin.jpg"
    ],
    "주소_정보": {
      "전체주소": "서울특별시 강동구 길동"
    },
    "평면도_URL": [],
    "거래_정보": {
      "거래방식": "월세   1,000만원/70만원",
      "관리비": "2만원",
      "입주가능일": "2025. 10. 25. 이후 (협의가능)"
    },
    "매물_정보": {
      "건물형태": "상가/사무실",
      "전용/계약면적": "3.31m2/3.31m2 (1평/1평)",
      "해당층/전체층": "1층/1층",
      "점포(사무실)개수": "1개",
      "화장실개수": "0개",
      "주차": "가능",
      "위반건축물 여부": "-",
      "난방방식": "개별난방",
      "냉방시설": "-",
      "보안시설": "-",
      "기타시설": "-"
    },
    "추가_옵션": [],
    "주변_학교": [],
    "상세_설명": "길동역 도보 5분, 정성껏 채워온 공간 양도합니다. ​ 작년 여름, 처음부터 직접 인테리어 공사하며 하나하나 만들어낸 매장입니다. 따뜻한 분위기와 세심하게 꾸며진 인테리어 덕분에 단골 손님뿐 아니라 쇼핑몰 촬영, 외국인 고객도 자주 찾는 공간이 되었습니다. ​ 특히 폴딩도어를 활짝 열면 개방감이 살아나며, 유럽 골목의 카페 같은 무드를 연출할 수 있습니다. 카페 운영은 물론이고, 공방, 꽃집, 소규모 편집숍, 클래스 공간, 스튜디오, 팝업스토어 등 다양한 콘셉트로 활용하기에 최적화된 공간입니다. 실내외 공간을 모두 활용할 수 있어 행사나 클래스 진행 시에도 장점이 큽니다. ​ 현재는 일반음식점으로 신고되어 있어 주류 판매도 가능하며, 냉난방기·조명·기본 주방설비가 갖춰져 있어 별도의 큰 공사 없이 바로 영업이 가능한 완성형 매장입니다. 공사와 인테리어에 이미 큰 비용과 시간이 들어가 있어, 인수 시 초기 투자 부담을 크게 줄일 수 있습니다. ​ 현재는 기존 매장 운영과 원두 납품 업무, 이사로 인한 거리 문제로 두 공간을 병행하기 어려워져 양도를 결심하게 되었습니다. 필요하신 경우 커피 및 음료 레시피 교육도 도와드릴 수 있으며, 장비 리스트 및 내부 사진은 문의 주시면 상세히 전달드리겠습니다. ​ 이 공간을 아껴주고 잘 활용해주실 분을 기다립니다. 방문은 사전 연락 후 가능하니 편하게 문의 주세요. ​ [공간 정보] • 위치: 서울 강동구 길동 / 길동역 도보 약 5분 • 구조: 1층 코너 / 폴딩도어 / 어닝 / 외부 공간 활용 가능 • 주차: 건물 앞 1대 가능 • 활용: 카페, 소규모 작업실, 촬영 공간, 공방 등 • 운영 특징: 단골 위주 운영 / 대관 수익 가능 • 양도 범위: 인테리어, 집기, 레시피 등 협의 • 양도 사유: 개인사정으로 인한 정리 ​"
  },
  {
    "중개사_정보": {},
    "매물번호": "18323007",
    "매물_URL": "https://www.peterpanz.com/house/18323007",
    "매물_이미지": [
      "https://img.peterpanz.com/photo/20251028/18323007/55ce7a2e4a4326f91e7fc55facc20fff_origin.jpg",
      "https://img.peterpanz.com/photo/20251028/18323007/73d50b0823047afad2cbcdd9e7212d7d_origin.jpg",
      "https://img.peterpanz.com/photo/20251028/18323007/4701a36160b7f00e3c97ca39f57277c5_origin.jpg",
      "https://img.peterpanz.com/photo/20251028/18323007/0455582572b3e6ab221d1875057a582d_origin.jpg"
    ],
    "주소_정보": {
      "전체주소": "서울특별시 강동구 암사동"
    },
    "평면도_URL": [],
    "거래_정보": {
      "거래방식": "월세   3,000만원/150만원",
      "관리비": "3만원 관리비 별도 전기, 수도, 가스",
      "융자금": "시세 대비 30% 미만",
      "입주가능일": "즉시입주 (협의가능)"
    },
    "매물_정보": {
      "건축물용도": "제2종 근린생활시설",
      "건물형태": "복합상가",
      "전용/계약면적": "56.2m2/56.2m2 (17평/17평)",
      "해당층/전체층": "1층/4층",
      "점포(사무실)개수": "0개",
      "화장실개수": "1개",
      "주된출입구": "남향",
      "총주차대수": "1대",
      "주차": "가능",
      "위반건축물 여부": "위반건축물",
      "사용승인일": "2004",
      "난방방식": "-",
      "냉방시설": "스탠드에어컨",
      "보안시설": "CCTV, 현관보안",
      "기타시설": "소화기"
    },
    "추가_옵션": [
      "주차가능"
    ],
    "주변_학교": [],
    "상세_설명": "좋은위치에 자리한\n\n배달전문 업장입니다\n\n기물전체 신품이며\n\n에어컨40평대 , 45구냉동\n\n하부냉장 2 대\n\n화구및 서랍식냉장 1대\n\n린나이 취반기\n\n온장고 등\n\n기물 전체 양도조건입니다\n\n1년간 월매출 꾸준히 4000이상 나오고 있으며\n\n가스 파이프공사\n\n및 필요설비 다되어있습니다.\n\n시설물 전체양수시 권리 2000 입니다\n\n매장 컨디션 매우 깔끔합니다.\n\n이사로인한 영업불가로 내놓습니다\n\n주차는 1대 가능합니다.\n\n문의사항 문자주세요\n공일공 6이8이 오공9삼"
  },
  {
    "중개사_정보": {},
    "매물번호": "18121066",
    "매물_URL": "https://www.peterpanz.com/house/18121066",
    "매물_이미지": [
      "https://img.peterpanz.com/photo/20250918/18121066/72b15799df7346f006d0204e759f68be_origin.jpg",
      "https://img.peterpanz.com/photo/20250918/18121066/3d981a940756b51b95c0e5d6a4e8e1a4_origin.jpg",
      "https://img.peterpanz.com/photo/20250918/18121066/abc9fb36a7485ea664378ad5f372efc2_origin.jpg",
      "https://img.peterpanz.com/photo/20250918/18121066/e26bbb827210da790bf77eef99420a56_origin.jpg",
      "https://img.peterpanz.com/photo/20250918/18121066/07ceb66f650b4fc23e9b62e459e2d518_origin.jpg"
    ],
    "주소_정보": {
      "전체주소": "서울특별시 강동구 암사동"
    },
    "평면도_URL": [],
    "거래_정보": {
      "거래방식": "월세   1,000만원/50만원",
      "관리비": "없음 관리비 별도 전기, 수도",
      "융자금": "융자금 없음",
      "입주가능일": "즉시입주 (협의가능)"
    },
    "매물_정보": {
      "건축물용도": "단독주택",
      "건물형태": "일반상가",
      "전용/계약면적": "26.45m2/26.45m2 (8평/8평)",
      "해당층/전체층": "1층/4층",
      "점포(사무실)개수": "0개",
      "화장실개수": "1개",
      "주된출입구": "동향",
      "총주차대수": "1대",
      "주차": "가능",
      "위반건축물 여부": "위반건축물 아님",
      "사용승인일": "1997.06.27"
    },
    "추가_옵션": [
      "주차가능"
    ],
    "주변_학교": [],
    "상세_설명": "올해로 5년차 운영하고있는 8평정도의 개인카페입니다:)\n근방에 바로 암사시장과 암사역이 위치한 곳이라 카페위치가 빌라 골목길에 있지만 유동인구가 충분히 있는곳이고 오래 운영해온만큼 단골분들이 많습니다.\n\n힘든 코로나시절에 오픈하게되어 지금까지 5년째 열심히 애정을 쏟아 운영해온곳입니다\n확장이전으로 인하여 아쉬운 마음을 담아 매물을 내놓게되었습니다\n저의 애정이 담긴 이 공간을 이어서 해주셔도 좋고 본인만의 공간으로 다시 꾸려나가기에도 좋은 공간이지않을까싶습니다\n\n(권리금있음)\n\n진심 어린 관심있으신분들만 연락부탁드립니다 :)\n감사합니다."
  },
  {
    "중개사_정보": {
      "중개사명": "우리공인중개사사무소",
      "대표자": "우순영",
      "전화번호": "02-442-8343",
      "주소": "서울특별시 강동구 양재대로134길 7 1층",
      "등록번호": "9252-5969",
      "거래완료": "4건",
      "등록매물": "10건"
    },
    "매물번호": "18359911",
    "매물_URL": "https://www.peterpanz.com/house/18359911",
    "매물_이미지": [
      "https://img.peterpanz.com/photo/20240618/15638763/ba0e0fd3d722a3905d005287588441a1_origin.jpg",
      "https://img.peterpanz.com/photo/20240618/15638763/403f19dd573de83b93a59088471cb817_origin.jpg",
      "https://img.peterpanz.com/photo/20240618/15638763/1c288f13a74cd6b20ce104a9b2d32b59_origin.jpg",
      "https://img.peterpanz.com/photo/20240618/15638763/9ac626bd3eaf34496892fb8b76a8a113_origin.jpg",
      "https://img.peterpanz.com/photo/20240618/15638763/ed6f5416fb6d64b30156a1f4d40833e5_origin.jpg",
      "https://img.peterpanz.com/photo/20240513/15499849/666d3b9743d36_origin.jpg",
      "https://img.peterpanz.com/photo/20240513/15499849/666d3b97c4231_origin.jpg",
      "https://img.peterpanz.com/photo/20240618/15638763/7a76226aa254afa6ea8b3276d163b26b_origin.jpg",
      "https://img.peterpanz.com/photo/20250812/17911884/689a94a5263d3_origin.jpg",
      "https://img.peterpanz.com/photo/20250812/17911884/689a94a665292_origin.jpg",
      "https://img.peterpanz.com/photo/20250812/17911884/689a94a78c093_origin.jpg",
      "https://img.peterpanz.com/photo/20250812/17911884/689a94a8b3038_origin.jpg",
      "https://img.peterpanz.com/photo/20250812/17911884/689a94aa17691_origin.jpg"
    ],
    "주소_정보": {
      "전체주소": "서울특별시 강동구 명일동"
    },
    "평면도_URL": [],
    "거래_정보": {
      "거래방식": "월세   2,000만원/120만원",
      "관리비": "2만원 관리비 별도 전기, 수도",
      "융자금": "융자금 없음",
      "입주가능일": "즉시입주 (협의가능)"
    },
    "매물_정보": {
      "건축물용도": "제1종 근린생활시설",
      "건물형태": "중소형사무실",
      "전용/계약면적": "116.7m2/130m2 (35.3평/39.32평)",
      "해당층/전체층": "2층/4층",
      "점포(사무실)개수": "1개",
      "화장실개수": "1개",
      "주된출입구": "남향",
      "총주차대수": "3대",
      "주차": "가능",
      "위반건축물 여부": "위반건축물 아님",
      "사용승인일": "1989.11.04",
      "난방방식": "-",
      "냉방시설": "벽걸이에어컨",
      "보안시설": "방범창",
      "기타시설": "베란다, 소화기"
    },
    "추가_옵션": [
      "큰길가",
      "반려동물",
      "주차가능"
    ],
    "주변_학교": [],
    "상세_설명": "매물소개\n--2층 40평 실35평\n__ 세 아주 싸고 남향 아주 밝고 깔끔한 사무실입니다.. 샤시 등 브라인드 등 모두 올리모델링 함\n2층이라서 피부샾 사무실 창고 사진관 학원 개인 연습실 등 다 됩니다\n..업종자유\n싱크대 칸막이 사용가능 방마다에어컨 유\n굽은다리역3분 명일역4분 재래시장인근\n주차됨\n비번유\n연락주셔요~ 정말좋습니다"
  },
  {
    "중개사_정보": {
      "중개사명": "우리공인중개사사무소",
      "대표자": "우순영",
      "전화번호": "02-442-8343",
      "주소": "서울특별시 강동구 양재대로134길 7 1층",
      "등록번호": "9252-5969",
      "거래완료": "4건",
      "등록매물": "10건"
    },
    "매물번호": "18303816",
    "매물_URL": "https://www.peterpanz.com/house/18303816",
    "매물_이미지": [
      "https://img.peterpanz.com/photo/20231205/14891558/656ef9a230268_origin.jpg",
      "https://img.peterpanz.com/photo/20231205/14891558/656ef9a6a76b1_origin.jpg",
      "https://img.peterpanz.com/photo/20231205/14891558/656ef9a336908_origin.jpg",
      "https://img.peterpanz.com/photo/20231205/14891558/656ef9a182c73_origin.jpg",
      "https://img.peterpanz.com/photo/20231205/14891558/656ef9a0ec077_origin.jpg",
      "https://img.peterpanz.com/photo/20231205/14891558/656ef9a2af474_origin.jpg",
      "https://img.peterpanz.com/photo/20231205/14891558/656ef9a3bf4b8_origin.jpg",
      "https://img.peterpanz.com/photo/20231205/14891558/656ef9a447fe0_origin.jpg",
      "https://img.peterpanz.com/photo/20231205/14891558/656ef9a4add79_origin.jpg",
      "https://img.peterpanz.com/photo/20231205/14891558/656ef9a53aee9_origin.jpg",
      "https://img.peterpanz.com/photo/20231205/14891558/656ef9a5aa71d_origin.jpg",
      "https://img.peterpanz.com/photo/20231205/14891558/656ef9a63cad5_origin.jpg",
      "https://img.peterpanz.com/photo/20231205/14891558/656ef9a739893_origin.jpg",
      "https://img.peterpanz.com/photo/20231205/14891558/656ef9a7b1d44_origin.jpg",
      "https://img.peterpanz.com/photo/20231205/14891558/656ef9a832774_origin.jpg"
    ],
    "주소_정보": {
      "전체주소": "서울특별시 강동구 명일동"
    },
    "평면도_URL": [],
    "거래_정보": {
      "거래방식": "월세   3,000만원/220만원",
      "관리비": "70만원 관리비 별도 전기, 가스, 수도, 난방",
      "융자금": "융자금 없음",
      "입주가능일": "즉시입주 (협의가능)"
    },
    "매물_정보": {
      "건축물용도": "제2종 근린생활시설",
      "건물형태": "대형사무실",
      "건물명": "에이플러스",
      "전용/계약면적": "145.54m2/227m2 (44.02평/68.66평)",
      "해당층/전체층": "3층/7층",
      "점포(사무실)개수": "4개",
      "화장실개수": "2개",
      "주된출입구": "남동향",
      "총주차대수": "1대",
      "주차": "가능",
      "위반건축물 여부": "위반건축물 아님",
      "사용승인일": "2004.04.30",
      "난방방식": "개별난방",
      "냉방시설": "-",
      "보안시설": "현관보안, CCTV, 방범창",
      "기타시설": "화재경보기, 소화기"
    },
    "추가_옵션": [
      "큰길가",
      "엘리베이터",
      "주차가능"
    ],
    "주변_학교": [],
    "상세_설명": "굽은다리역인근 빌딩건물 대로변 가격 아주 좋습니다\n아주깔끔하고 넓고 밝고 조용합니다\n추천 용도: 사무실 ,병원 , 학원 스튜디오 샾 등 >>\n주위에 아파트 ,병원, 사무실 ,학원, 명성교인, 역세권 위치좋습니다\n원하시면 칸막이철거해드립니다\n언제든지 문의주시면 바로 안내해드립니다 연락주세요"
  },
  {
    "중개사_정보": {
      "중개사명": "우리공인중개사사무소",
      "대표자": "우순영",
      "전화번호": "02-442-8343",
      "주소": "서울특별시 강동구 양재대로134길 7 1층",
      "등록번호": "9252-5969",
      "거래완료": "4건",
      "등록매물": "10건"
    },
    "매물번호": "18032301",
    "매물_URL": "https://www.peterpanz.com/house/18032301",
    "매물_이미지": [
      "https://img.peterpanz.com/photo/20240722/15768882/669f15a3470ce_origin.jpg",
      "https://img.peterpanz.com/photo/20240722/15768882/669f15a3b1062_origin.jpg",
      "https://img.peterpanz.com/photo/20240131/15101953/65c18a71ca75e_origin.jpg",
      "https://img.peterpanz.com/photo/20240722/15768882/669f15a655426_origin.jpg",
      "https://img.peterpanz.com/photo/20240722/15768882/669f15a70b2e2_origin.jpg"
    ],
    "주소_정보": {
      "전체주소": "서울특별시 강동구 명일동"
    },
    "평면도_URL": [],
    "거래_정보": {
      "거래방식": "월세   500만원/55만원",
      "관리비": "1만원 관리비 별도 전기, 가스, 수도, 난방",
      "융자금": "융자금 없음",
      "입주가능일": "즉시입주 (협의가능)"
    },
    "매물_정보": {
      "건축물용도": "제2종 근린생활시설",
      "건물형태": "일반상가",
      "전용/계약면적": "24m2/28m2 (7.26평/8.47평)",
      "해당층/전체층": "2층/3층",
      "점포(사무실)개수": "1개",
      "화장실개수": "1개",
      "주된출입구": "남향",
      "총주차대수": "2대",
      "주차": "불가",
      "위반건축물 여부": "위반건축물 아님",
      "사용승인일": "1991.08.23",
      "난방방식": "개별난방",
      "냉방시설": "벽걸이에어컨",
      "보안시설": "현관보안, 방범창",
      "기타시설": "소화기"
    },
    "추가_옵션": [],
    "주변_학교": [],
    "상세_설명": "조용하고 아주밝고 깔끔합니다\n밖이 막힘없고 시원합니다\n내부 화장실 에어컨 싱크대 있어요\n주차는 상 하차만 가능\n연락주시면 바로 안내 해 드립니다~\n우리공인중개사 010-4037-8343"
  },
  {
    "중개사_정보": {
      "중개사명": "우리공인중개사사무소",
      "대표자": "우순영",
      "전화번호": "02-442-8343",
      "주소": "서울특별시 강동구 양재대로134길 7 1층",
      "등록번호": "9252-5969",
      "거래완료": "4건",
      "등록매물": "10건"
    },
    "매물번호": "18335924",
    "매물_URL": "https://www.peterpanz.com/house/18335924",
    "매물_이미지": [
      "https://img.peterpanz.com/photo/20251030/18335924/6902fb033724d_origin.jpg",
      "https://img.peterpanz.com/photo/20251030/18335924/6902fb0453fe2_origin.jpg",
      "https://img.peterpanz.com/photo/20251030/18335924/6902fb0555930_origin.jpg",
      "https://img.peterpanz.com/photo/20251030/18335924/6902fb066ebad_origin.jpg",
      "https://img.peterpanz.com/photo/20251030/18335924/6902fb078db7f_origin.jpg",
      "https://img.peterpanz.com/photo/20251030/18335924/6902fb08aa000_origin.jpg",
      "https://img.peterpanz.com/photo/20251030/18335924/6902fb09e0b1a_origin.jpg",
      "https://img.peterpanz.com/photo/20251030/18335924/6902fb0ad8e7a_origin.jpg",
      "https://img.peterpanz.com/photo/20251030/18335924/6902fb0bf1aaf_origin.jpg",
      "https://img.peterpanz.com/photo/20251030/18335924/6902fb0d22ca5_origin.jpg"
    ],
    "주소_정보": {
      "전체주소": "서울특별시 강동구 명일동"
    },
    "평면도_URL": [],
    "거래_정보": {
      "거래방식": "월세   1,500만원/110만원",
      "관리비": "8만원 관리비 별도 전기, 수도",
      "융자금": "융자금 없음",
      "입주가능일": "즉시입주 (협의가능)"
    },
    "매물_정보": {
      "건축물용도": "제2종 근린생활시설",
      "건물형태": "중소형사무실",
      "전용/계약면적": "75m2/80m2 (22.69평/24.2평)",
      "해당층/전체층": "3층/3층",
      "점포(사무실)개수": "1개",
      "화장실개수": "1개",
      "주된출입구": "동향",
      "총주차대수": "6대",
      "주차": "가능",
      "위반건축물 여부": "위반건축물 아님",
      "사용승인일": "1984.07.30",
      "난방방식": "-",
      "냉방시설": "천장에어컨",
      "보안시설": "현관보안, 방범창",
      "기타시설": "소화기"
    },
    "추가_옵션": [
      "주차가능"
    ],
    "주변_학교": [],
    "상세_설명": "아주아주 깔끔한 사무실\n개인스트디오 피부샾 등 추천\n대로변이고 건널목앞이라 유동많고 광고효과 좋은위치입니다\n싱크대 유\n연락주셔요~~\n바로 볼수있습니다"
  },
  {
    "중개사_정보": {},
    "매물번호": "18281407",
    "매물_URL": "https://www.peterpanz.com/house/18281407",
    "매물_이미지": [
      "https://img.peterpanz.com/photo/20250213/16947938/20c6430f558d3897c9700a79942c8a0e_origin.jpg",
      "https://img.peterpanz.com/photo/20250213/16947938/194f551b2410045ea7ec4f75fc436f50_origin.jpg",
      "https://img.peterpanz.com/photo/20250213/16947938/df82dce1b4bad77ac1f5d1e2e22dfe5a_origin.jpg",
      "https://img.peterpanz.com/photo/20250213/16947938/2ddd97cb1753ead2968456d75e37fc48_origin.jpg",
      "https://img.peterpanz.com/photo/20250213/16947938/fe68e386b9eae5b2e145b2a03cc10a3f_origin.jpg"
    ],
    "주소_정보": {
      "전체주소": "서울특별시 강동구 명일동"
    },
    "평면도_URL": [],
    "거래_정보": {
      "거래방식": "월세   4,000만원/260만원",
      "관리비": "35만원 관리비 별도 난방, 전기, 수도, 가스",
      "융자금": "융자금 없음",
      "입주가능일": "즉시입주 (협의가능)"
    },
    "매물_정보": {
      "건축물용도": "제1종 근린생활시설",
      "건물형태": "단지내상가",
      "건물명": "한화오벨리스크스위트",
      "전용/계약면적": "49.37m2/49.37m2 (14.93평/14.93평)",
      "해당층/전체층": "1층/15층",
      "점포(사무실)개수": "1개",
      "화장실개수": "2개",
      "주된출입구": "북동향",
      "총주차대수": "1대",
      "주차": "불가",
      "위반건축물 여부": "위반건축물 아님",
      "사용승인일": "2005.10.18",
      "난방방식": "개별난방",
      "냉방시설": "벽걸이에어컨, 천장에어컨",
      "보안시설": "CCTV, 카드키, 자체경비원",
      "기타시설": "화재경보기, 무인택배함, 소화기"
    },
    "추가_옵션": [
      "큰길가",
      "엘리베이터"
    ],
    "주변_학교": [],
    "상세_설명": "마진율 높은 로스터리 양도, 사계절 로스팅 프로파일 확보, 초보자도 가능합니다.\n\n\n\n권리금 2800만\n보증금 4000만 / 월세 260만\n\n\n\n\n5호선 고덕역, 강동경희대학병원, 강동아트센터 도보 5분이내\n\n\n매물 특징 : 로스터기 설치로 인한, 380v 전기 증설완료\n/ 현재, 지하 1층 60분 무료주차 가능 ( 이후 시간 늘어날 여지있음 )\n\n인수인계 가능 부분 : 원팩화 레시피, 운영을 위한 모든부분\n( 시그니처 상품포함 )\n\n\n\n[ 매물 설명 ]\n- (24년 8월 리뉴얼) 주문제작 6인 Bar 테이블, 모든 테이블과 의자, ( 4인석 2개 / 2인석 6개 )\n- 빈티지 골동품 약 100점과 빈티지 커피잔 세트\n- Ek43 리테일 그라인더, 달라코르테 XT 유량조절 2그룹 에스프레소머신, 안핌 Alba 그라인더, 추출관련 도구들 ( 예, 니들 디스트리뷰터, 자동 탬핑기 등 )\n- 후지로얄 R 103 반열풍 로스터기, 브레마 제빙기, 에베레스트 냉장고 등 전부 포함 사항입니다.\n\n\n\n현재 매장운영시간 08시 ~ 18시, 반오토 시스템입니다.\n\n더 자세한 문의는 전화주시면 감사하겠습니다.\n\n( 개인연락처로 문의주시면 감사하겠습니다 )"
  },
  {
    "중개사_정보": {},
    "매물번호": "18306314",
    "매물_URL": "https://www.peterpanz.com/house/18306314",
    "매물_이미지": [
      "https://img.peterpanz.com/photo/20251024/18306314/68fb4ec071bb5_origin.jpg",
      "https://img.peterpanz.com/photo/20251024/18306314/68fb4ec0d5093_origin.jpg",
      "https://img.peterpanz.com/photo/20251024/18306314/68fb4ec161490_origin.jpg",
      "https://img.peterpanz.com/photo/20251024/18306314/68fb4ec1d444f_origin.jpg",
      "https://img.peterpanz.com/photo/20251024/18306314/68fb4ec25daff_origin.jpg",
      "https://img.peterpanz.com/photo/20251024/18306314/68fb4ec2d3340_origin.jpg",
      "https://img.peterpanz.com/photo/20251024/18306314/68fb4ec3562ac_origin.jpg",
      "https://img.peterpanz.com/photo/20251024/18306314/68fb4ec3cd7d8_origin.jpg",
      "https://img.peterpanz.com/photo/20251024/18306314/68fb4ec44e381_origin.jpg",
      "https://img.peterpanz.com/photo/20251024/18306314/68fb4ec4d056a_origin.jpg",
      "https://img.peterpanz.com/photo/20251024/18306314/68fb4ec54cfa2_origin.jpg",
      "https://img.peterpanz.com/photo/20251024/18306314/68fb4ec5af47a_origin.jpg",
      "https://img.peterpanz.com/photo/20251024/18306314/68fb4ec628421_origin.jpg",
      "https://img.peterpanz.com/photo/20251024/18306314/68fb4ec696692_origin.jpg",
      "https://img.peterpanz.com/photo/20251024/18306314/68fb4ec6f2fe8_origin.jpg"
    ],
    "주소_정보": {
      "전체주소": "경기도 하남시 풍산동"
    },
    "평면도_URL": [],
    "거래_정보": {
      "거래방식": "매매   1억 2,000만원",
      "관리비": "10만원 관리비 별도 전기, 난방",
      "융자금": "융자금 없음",
      "입주가능일": "즉시입주 (협의가능)"
    },
    "매물_정보": {
      "건축물용도": "제1종 근린생활시설",
      "건물형태": "중소형사무실",
      "전용/계약면적": "12m2/72.73m2 (3.63평/22평)",
      "해당층/전체층": "2층/10층",
      "점포(사무실)개수": "1개",
      "화장실개수": "1개",
      "주된출입구": "동향",
      "총주차대수": "300대",
      "주차": "가능",
      "위반건축물 여부": "위반건축물 아님",
      "사용승인일": "2019.02",
      "난방방식": "중앙난방",
      "냉방시설": "천장에어컨",
      "보안시설": "현관보안, CCTV",
      "기타시설": "화재경보기, 무인택배함, 소화기"
    },
    "추가_옵션": [
      "주차가능"
    ],
    "주변_학교": [],
    "상세_설명": "건물부근에 한올중학교 정문쪽이며 교습소도 가능\n상일IC에서 200미터 거리입니다.\n현재 세입자가 사무실로 사용하고 있으며\n보증금 525만 월세 60,600원(부가세포함)\n1년씩 계약이므로 매년 보증금과 월세를 각각 5%씩 인상하고 있습니다.\n이 건물상가중 가장 좋은 위치의 사무실 219호입니다.\n천장에어컨으로 냉난방 가능.\n정사각으로 반듯하며 산이 멀리 보이는 풍광\n바로 옆에 주유소라 트여있어서 유리이며 3면 모두 광고문구 가능(한면은 복도)\n복도에서 사무실 안쪽이 잘 보이므로 직접 가보시기 바랍니다.\n6년전 분양가 1억 3000\n현재 매매가 1억 2000\n계약은 안전하게 부동산에서 합니다.\n부동산수수료는 개인간계약으로 약간의 수수료만 지급\n현장 주소는 경기도 하남시 조정대로 85 (풍산동 529)\n문의는 공일공 삼칠일칠 육칠일칠"
  },
  {
    "중개사_정보": {},
    "매물번호": "18375054",
    "매물_URL": "https://www.peterpanz.com/house/18375054",
    "매물_이미지": [
      "https://img.peterpanz.com/photo/20250721/17843804/178e36e41eac7f96e058d62656bfa22b_origin.jpg",
      "https://img.peterpanz.com/photo/20250721/17843804/d52e1cada3135f9b94fe492a6f7ec758_origin.jpg",
      "https://img.peterpanz.com/photo/20250721/17843804/d15a90b15c9e7dbff817bf82fa787b0c_origin.jpg",
      "https://img.peterpanz.com/photo/20250721/17843804/9c5382e49971c99600717df166267634_origin.jpg",
      "https://img.peterpanz.com/photo/20250721/17843804/7f849487d8c1909311112a5361c4a9db_origin.jpg",
      "https://img.peterpanz.com/photo/20250721/17843804/caa0b99595efb372a016f8b289a6667c_origin.jpg",
      "https://img.peterpanz.com/photo/20250721/17843804/d59fa291586e08b847c3a7de839d67b0_origin.jpg",
      "https://img.peterpanz.com/photo/20250721/17843804/12693fc6ee6ff1586df6ca054230b80d_origin.jpg"
    ],
    "주소_정보": {
      "전체주소": "서울특별시 강동구 고덕동"
    },
    "평면도_URL": [],
    "거래_정보": {
      "거래방식": "월세   1,000만원/180만원",
      "관리비": "없음",
      "융자금": "-",
      "입주가능일": "즉시입주"
    },
    "매물_정보": {
      "건축물용도": "업무시설",
      "건물형태": "오피스텔형",
      "전용/계약면적": "46m2/67m2 (13.91평/20.27평)",
      "해당층/전체층": "9층/21층",
      "점포(사무실)개수": "1개",
      "화장실개수": "1개",
      "주된출입구": "북향",
      "총주차대수": "1대",
      "주차": "가능",
      "위반건축물 여부": "위반건축물 아님",
      "사용승인일": "2025.02.21",
      "난방방식": "개별난방",
      "냉방시설": "천장에어컨",
      "보안시설": "현관보안, CCTV, 인터폰, 자체경비원",
      "기타시설": "화재경보기, 무인택배함, 테라스, 소화기"
    },
    "추가_옵션": [
      "주차가능"
    ],
    "주변_학교": [],
    "상세_설명": "이케아 위치한 현대아이파크 더리버 9층 영구 한강뷰 하이엔드 오피스입니다\n\n\n공간정보(즉시 입주 가능)\n● 공급 67m²(20.3평) / 전용 46m²(13.9평)\n9층(총 21층)\n● 북향(영구 한강 뷰) / 개별 테라스\n● 복도 아닌 9층 홀 앞에 위치하여 개방감 좋음\n● 엘레베이터 인근\n\n시설정보\n● 단독 화장실 및 샤워실\n● 단독 세탁기 건조기\n● 천장 에어콘(개별 조절가능)\n● 싱크대, 냉장고\n● 미러월패드(실내 시스템 조절 패드) 등\n\n임대조건(기간/금액 협의 가능)\n● 보증금 1,000만원\n● 월세 180만원\n● 관리비: 실 청구분 임차인 납부\n\n주차정보\n● 전용 1대 등록 가능\n● 방문 주차권 매월 150시간 제공\n\n건물 내 시설\n● 이케아(서울 유일), 이마트, 다이소, CGV, 무신사\n● 편의점(GS25), 전문식당가, 아웃백, 빕스, 아크앤북,\n스타벅스 등 다수 카페\n● 인피니티풀, 헬스장, 골프연습장, 사우나\n● 입주자 전용 공유키친, 정원, 미팅룸 등\n건물 내 원스탑 라이프 가능\n\n문의\n● 부담없이 언제든 연락주시면 즉시 응대 드리겠습니다^^\n\n010 2216 6595\n010 8944 7909"
  },
  {
    "중개사_정보": {},
    "매물번호": "18372749",
    "매물_URL": "https://www.peterpanz.com/house/18372749",
    "매물_이미지": [
      "https://img.peterpanz.com/photo/20251105/18372749/58b7b15b6eb86c67c8dc5bc49399e974_origin.jpg",
      "https://img.peterpanz.com/photo/20251105/18372749/f7b30395ab37191ae8ddd9be0e3f2dd3_origin.jpg",
      "https://img.peterpanz.com/photo/20251105/18372749/e53841ca9bb4cf335fcd91dc9c06824e_origin.jpg",
      "https://img.peterpanz.com/photo/20251105/18372749/56c5aaa9d7dc65e822bf309da1e37fa4_origin.jpg",
      "https://img.peterpanz.com/photo/20251105/18372749/63403a2af6826190fdeb19a2e00cfbab_origin.jpg",
      "https://img.peterpanz.com/photo/20251105/18372749/ec5ffdaccef8b3822b844ef0601805d4_origin.jpg",
      "https://img.peterpanz.com/photo/20251105/18372749/91669412438a95117ea238fc8dfad8d2_origin.jpg",
      "https://img.peterpanz.com/photo/20251105/18372749/661b0d1b3568840c7187b0618fe21f32_origin.jpg",
      "https://img.peterpanz.com/photo/20251105/18372749/552b630c3648f5e0a89f52605eb86e8d_origin.jpg",
      "https://img.peterpanz.com/photo/20251105/18372749/75b639292aad258f7dda9a3e0e9d3e05_origin.jpg"
    ],
    "주소_정보": {
      "전체주소": "경기도 하남시 망월동"
    },
    "평면도_URL": [],
    "거래_정보": {
      "거래방식": "월세   3,000만원/200만원",
      "관리비": "40만원",
      "융자금": "-",
      "입주가능일": "2025. 12. 19. 이후 (협의가능)"
    },
    "매물_정보": {
      "건축물용도": "제1종 근린생활시설",
      "건물형태": "오피스텔형",
      "전용/계약면적": "61.27m2/130m2 (18.53평/39.32평)",
      "해당층/전체층": "3층/13층",
      "점포(사무실)개수": "1개",
      "화장실개수": "2개",
      "주된출입구": "남서향",
      "총주차대수": "1대",
      "주차": "가능",
      "위반건축물 여부": "위반건축물 아님",
      "사용승인일": "2019.07.01",
      "난방방식": "개별난방",
      "냉방시설": "-",
      "보안시설": "-",
      "기타시설": "-"
    },
    "추가_옵션": [
      "주차가능"
    ],
    "주변_학교": [],
    "상세_설명": "5호선 미사역 부근 신한은행 입주건물\n3층 중심상가 초입 /대로변 대단지 아파트 사거리\n유동인구 많음,\n현재 헤어샵 영업중 ,12월19일이후 원상복구예정\n준공이후 공실없이 임대중"
  },
  {
    "중개사_정보": {},
    "매물번호": "18311994",
    "매물_URL": "https://www.peterpanz.com/house/18311994",
    "매물_이미지": [
      "https://img.peterpanz.com/photo/20250924/18157159/68d3f666e9f76_origin.jpg",
      "https://img.peterpanz.com/photo/20250924/18157159/68d3f667415c0_origin.jpg",
      "https://img.peterpanz.com/photo/20250924/18157159/68d3f667a0b6c_origin.jpg"
    ],
    "주소_정보": {
      "전체주소": "경기도 하남시 망월동"
    },
    "평면도_URL": [],
    "거래_정보": {
      "거래방식": "매매   2억 8,000만원",
      "관리비": "40만원",
      "융자금": "1억 8,000만원 (시세 대비 30% 이상)",
      "입주가능일": "2027. 09. 13. 이후"
    },
    "매물_정보": {
      "건축물용도": "제2종 근린생활시설",
      "건물형태": "일반상가",
      "전용/계약면적": "76.77m2/148.77m2 (23.22평/45평)",
      "해당층/전체층": "5층/5층",
      "점포(사무실)개수": "1개",
      "화장실개수": "1개",
      "주된출입구": "북향",
      "총주차대수": "16대",
      "주차": "가능",
      "위반건축물 여부": "위반건축물 아님",
      "사용승인일": "2018.04.02"
    },
    "추가_옵션": [
      "주차가능"
    ],
    "주변_학교": [],
    "상세_설명": "*부동산종류: 상가\n*면적: 45.06(전용23.22)평\n*금액: 2.8억원 vat 별도\n*문의 연락처: 010-4568-9171\n*부동산 장점:\n- 항아리 상권으로 영어학원이 5년째 운영중이며 계속 성장 중\n- 25년 9월 기존 임대액에서 5%증액하여 재계약 완료 계약기간 2년 남은 우량 상가\n*임차금액: 2천/126만(vat별도)"
  },
  {
    "중개사_정보": {},
    "매물번호": "18331707",
    "매물_URL": "https://www.peterpanz.com/house/18331707",
    "매물_이미지": [
      "https://img.peterpanz.com/photo/20220928/13421802/552c00dafc08d55a995d68961045af2e_origin.jpg",
      "https://img.peterpanz.com/photo/20220928/13421802/6524e799c3a59fafa8cd18457ddd1fcf_origin.jpg",
      "https://img.peterpanz.com/photo/20220928/13421802/279b3ff550df4d34c4834c5ef71f0b98_origin.jpg",
      "https://img.peterpanz.com/photo/20220928/13421802/765a92be7c308a664b3a8618a34b65fc_origin.jpg"
    ],
    "주소_정보": {
      "전체주소": "경기도 하남시 망월동"
    },
    "평면도_URL": [],
    "거래_정보": {
      "거래방식": "매매   15억 분양금액 12억 프리미엄금액 3억 분양옵션금액 -",
      "관리비": "20만원 관리비 별도 난방, 전기, 수도, 가스",
      "융자금": "6억 4,200만원 (시세 대비 30% 미만)",
      "입주가능일": "즉시입주 (협의가능)"
    },
    "매물_정보": {
      "분양권": "일반분양",
      "건축물용도": "제2종 근린생활시설",
      "건물형태": "복합상가",
      "건물명": "우성르보아파크",
      "전용/계약면적": "119.02m2/238.03m2 (36평/72평)",
      "해당층/전체층": "2층/18층",
      "점포(사무실)개수": "1개",
      "화장실개수": "6개",
      "주된출입구": "남동향",
      "총주차대수": "509대",
      "주차": "가능",
      "위반건축물 여부": "위반건축물 아님",
      "사용승인일": "2018.05.30",
      "난방방식": "개별난방, 지역난방",
      "냉방시설": "천장에어컨, 벽걸이에어컨",
      "보안시설": "-",
      "기타시설": "화재경보기, 무인택배함, 소화기"
    },
    "추가_옵션": [
      "주차가능"
    ],
    "주변_학교": [],
    "상세_설명": "샤브샤브, 참치,이자카야,병원,커피숍, 사무실 등\n모두 적합 운동장 신호등 에서,도로 에서 잘보인\n현재 샤브샤브 운영중"
  }
]