[
  {
    "중개사_정보": {
      "중개사명": "다원공인중개사사무소",
      "대표자": "김소윤",
      "전화번호": "010-3199-9478",
      "주소": "서울특별시 은평구 역말로 62 1층 1호",
      "등록번호": "11380-2018-00070",
      "거래완료": "1102건",
      "등록매물": "74건"
    },
    "매물번호": "18450724",
    "매물_URL": "https://www.peterpanz.com/house/18450724",
    "매물_이미지": [
      "https://img.peterpanz.com/photo/20230727/14456695/64c22052e97e2_origin.jpg",
      "https://img.peterpanz.com/photo/20230727/14456695/64c2205381fc5_origin.jpg",
      "https://img.peterpanz.com/photo/20230727/14456695/64c22054203b2_origin.jpg",
      "https://img.peterpanz.com/photo/20230727/14456695/64c22054a5db6_origin.jpg",
      "https://img.peterpanz.com/photo/20230727/14456695/64c2205531958_origin.jpg",
      "https://img.peterpanz.com/photo/20230727/14456695/64c22055c239a_origin.jpg",
      "https://img.peterpanz.com/photo/20230727/14456695/64c220565bc91_origin.jpg",
      "https://img.peterpanz.com/photo/20230727/14456695/64c22056e9de1_origin.jpg",
      "https://img.peterpanz.com/photo/20230727/14456695/64c2205763f9f_origin.jpg",
      "https://img.peterpanz.com/photo/20230727/14456695/64c22057d95c0_origin.jpg",
      "https://img.peterpanz.com/photo/20230727/14456695/64c220588640c_origin.jpg",
      "https://img.peterpanz.com/photo/20230727/14456695/64c2205932d08_origin.jpg"
    ],
    "주소_정보": {
      "전체주소": "서울특별시 은평구 신사동 30-51 아줄리움"
    },
    "평면도_URL": [],
    "거래_정보": {
      "거래방식": "월세   3,000만원/120만원",
      "관리비": "기타 부과 8만원  정액 관리비가 10만원 미만인 경우 포함 항목 공용관리비, 인터넷, TV 관리비 기준: 최근 1년 관리비 평균금액",
      "융자금": "-",
      "입주가능일": "즉시입주 (협의가능)"
    },
    "매물_정보": {
      "전입신고 여부": "가능",
      "전용/공급면적": "28.81m2/43.82m2 (8.71평/13.25평)",
      "건축물용도": "업무시설",
      "오피스텔명": "아줄리움",
      "동": "1동",
      "해당층/전체층": "7층/11층",
      "방/욕실개수": "2개/1개",
      "방거실형태": "분리형",
      "주실기준/방향": "거실/남동향",
      "현관유형": "복합식",
      "총세대수": "30세대",
      "총주차대수": "17대",
      "주차": "가능",
      "사용승인일": "2022.07.29",
      "난방방식": "개별난방",
      "냉방시설": "천장에어컨",
      "생활시설": "냉장고, 세탁기, 싱크대, 붙박이장, 신발장, 인덕션레인지, 건조기, 식탁",
      "보안시설": "현관보안, CCTV, 인터폰, 비디오폰, 카드키, 방범창, 사설경비",
      "기타시설": "화재경보기, 무인택배함, 베란다, 소화기"
    },
    "추가_옵션": [
      "신축",
      "풀옵션",
      "큰길가",
      "엘리베이터",
      "반려동물",
      "전세자금대출",
      "주차가능"
    ],
    "주변_학교": [],
    "상세_설명": "🚨초역세권 큰길가 특급매물 드디어 떴다 🚨\n\n🏡 위치 및 입지조건\n- 새절역 도보 5분, 은평 이마트, 불광천 등\n- 기계식 주차타워 주차 가능\n\n🏠 구조 및 옵션내역\n- 방2 거실1 화장실1 다용도실1\n- 시스템에어컨 , 신발장, 냉장고 , 세탁기 , 건조기 , 인덕션레인지, 중문 등\n\n🏘️\b 추천 포인트\n- 급매물 정말 좋은 가격 빠른 입주 완전 조율 가능\n- 전입신고, 확정일자, 최우선변제 가능한 안전 매물\n\n▪중기청, 안심전세, 신축전세대출 상담및 조회 가능 ▪\n▪신혼부부, 1인가구 등 추천 매물 다량 보유 부동산 ▪"
  },
  {
    "중개사_정보": {
      "중개사명": "주식회사세움부동산중개법인",
      "대표자": "권형선",
      "전화번호": "010-3319-3575",
      "주소": "서울특별시 중랑구 면목동 119-4 1층 101호",
      "등록번호": "11260202400012",
      "거래완료": "133건",
      "등록매물": "115건"
    },
    "매물번호": "18414825",
    "매물_URL": "https://www.peterpanz.com/house/18414825",
    "매물_이미지": [
      "https://img.peterpanz.com/photo/20250124/16838695/67a0769c8fff8_origin.jpg",
      "https://img.peterpanz.com/photo/20250124/16838695/67a0769d0f2e3_origin.jpg",
      "https://img.peterpanz.com/photo/20250124/16838695/67a0769d92880_origin.jpg",
      "https://img.peterpanz.com/photo/20250124/16838695/67a0769e2230e_origin.jpg",
      "https://img.peterpanz.com/photo/20250124/16838695/67a0769e965c1_origin.jpg",
      "https://img.peterpanz.com/photo/20250124/16838695/67a0769f146c1_origin.jpg",
      "https://img.peterpanz.com/photo/20250124/16838695/67a0769f899e6_origin.jpg",
      "https://img.peterpanz.com/photo/20250124/16838695/67a076a00a140_origin.jpg",
      "https://img.peterpanz.com/photo/20250124/16838695/67a076a0840b2_origin.jpg",
      "https://img.peterpanz.com/photo/20250124/16838695/67a076a1039d6_origin.jpg",
      "https://img.peterpanz.com/photo/20250124/16838695/67a076a174a0c_origin.jpg"
    ],
    "주소_정보": {
      "전체주소": "서울특별시 은평구 신사동 30-51 아줄리움"
    },
    "평면도_URL": [],
    "거래_정보": {
      "거래방식": "월세   3,000만원/120만원",
      "관리비": "기타 부과 6만원  관리규약 등에 따라 부과 포함 항목 공용관리비, TV, 인터넷 관리비 기준: 직전 월 관리비 부과금액",
      "융자금": "-",
      "입주가능일": "즉시입주 (협의가능)"
    },
    "매물_정보": {
      "전입신고 여부": "-",
      "전용/공급면적": "28.81m2/43.82m2 (8.71평/13.25평)",
      "건축물용도": "업무시설",
      "오피스텔명": "아줄리움",
      "동": "1동",
      "해당층/전체층": "7층/11층",
      "방/욕실개수": "2개/1개",
      "방거실형태": "오픈형",
      "주실기준/방향": "거실/남향",
      "현관유형": "-",
      "총세대수": "30세대",
      "총주차대수": "30대 (세대당 1대)",
      "주차": "가능",
      "사용승인일": "2022.07.29",
      "난방방식": "개별난방",
      "냉방시설": "천장에어컨",
      "생활시설": "냉장고, 세탁기, 싱크대, 신발장, 인덕션레인지, 건조기",
      "보안시설": "현관보안, CCTV, 인터폰, 비디오폰",
      "기타시설": "화재경보기, 무인택배함, 소화기"
    },
    "추가_옵션": [
      "풀옵션",
      "큰길가",
      "엘리베이터",
      "반려동물",
      "주차가능"
    ],
    "주변_학교": [],
    "상세_설명": "💖 💖세움은 주말,공휴일 늦은시간에 관계없이 언제든 매물을 보실수 있습니다💖💖\n\n💖 세움은 허위매물 절대NO! 직접 현장답사한 실사진 실매물입니다\n💖 세움은 내집 구한다는 생각으로 끝까지 정성을 다해 꼼꼼히 중개합니다.\n💖 세움은 정확한 정보만을 정직하게 전달합니다.\n💖 세움은 고객님의 입장에서 안전한 매물만을 중개합니다.\n💖 세움은 정확한 권리관계 분석으로 소중한 재산을 지켜드립니다.\n💖 등기부등본,건축물대장 확인은 기본중의 기본으로 진행합니다.\n💖 한국공인중개사협회 공제증서 교부 해드립니다."
  },
  {
    "중개사_정보": {
      "중개사명": "파크부동산공인중개사사무소",
      "대표자": "박재환",
      "전화번호": "010-6231-3334",
      "주소": "서울특별시 은평구 역촌동 21-4 51(역촌동), 1층 우측끝",
      "등록번호": "11380-2022-00006",
      "거래완료": "423건",
      "등록매물": "23건"
    },
    "매물번호": "18303750",
    "매물_URL": "https://www.peterpanz.com/house/18303750",
    "매물_이미지": [
      "https://img.peterpanz.com/photo/20250326/17211469/67e3b6e33756b_origin.jpg",
      "https://img.peterpanz.com/photo/20250326/17211469/67e3b6e3eb6aa_origin.jpg",
      "https://img.peterpanz.com/photo/20250326/17211469/67e3b6e48a1e8_origin.jpg",
      "https://img.peterpanz.com/photo/20250326/17211469/67e3b6e559f1f_origin.jpg",
      "https://img.peterpanz.com/photo/20250326/17211469/67e3b6e5d9093_origin.jpg",
      "https://img.peterpanz.com/photo/20250326/17211469/67e3b6e6846d6_origin.jpg",
      "https://img.peterpanz.com/photo/20250326/17211469/67e3b6e71f8b5_origin.jpg",
      "https://img.peterpanz.com/photo/20250326/17211469/67e3b6e7a60bb_origin.jpg",
      "https://img.peterpanz.com/photo/20250326/17211469/67e3b6e852918_origin.jpg",
      "https://img.peterpanz.com/photo/20250326/17211469/67e3b6e926d9a_origin.jpg"
    ],
    "주소_정보": {
      "전체주소": "서울특별시 은평구 신사동 30-51 아줄리움"
    },
    "평면도_URL": [],
    "거래_정보": {
      "거래방식": "매매   3억 2,000만원",
      "관리비": "관리비 합계 정액 관리비 10만원 공용 관리비 10만원 (정액부과) 사용료 전기 사용량에 따라 별도 부과 수도 사용량에 따라 별도 부과 가스 사용량에 따라 별도 부과 난방 사용량에 따라 별도 부과 인터넷 사용량에 따라 별도 부과 TV 사용량에 따라 별도 부과 관리비 기준: 직전 월 관리비 부과금액",
      "융자금": "-",
      "입주가능일": "즉시입주"
    },
    "매물_정보": {
      "전용/공급면적": "29.45m2/45.14m2 (8.91평/13.65평)",
      "건축물용도": "업무시설",
      "오피스텔명": "아줄리움",
      "동": "1동",
      "해당층/전체층": "10층/11층",
      "방/욕실개수": "2개/1개",
      "주실기준/방향": "거실/남향",
      "현관유형": "복합식",
      "총세대수": "30세대",
      "총주차대수": "17대 (세대당 0.57대)",
      "주차": "가능",
      "사용승인일": "2022.07.29",
      "난방방식": "개별난방",
      "냉방시설": "천장에어컨",
      "생활시설": "냉장고, 세탁기, 싱크대, 신발장, 인덕션레인지, 건조기",
      "보안시설": "CCTV, 인터폰, 비디오폰, 카드키",
      "기타시설": "화재경보기, 무인택배함, 베란다, 소화기"
    },
    "추가_옵션": [
      "신축",
      "풀옵션",
      "큰길가",
      "엘리베이터",
      "반려동물",
      "전세자금대출",
      "주차가능"
    ],
    "주변_학교": [],
    "상세_설명": "⭐신축오피스텔 / 서부선 개통 예정 / 풀옵션⭐\n\n💖실거주 가능 / 전월세 투자 가능\n월세 5,000 / 100만원 수준으로 투자 가능\n💖특례보금자리론 내생애최초 70% 담보대출 가능\n💖취득세 100% 지원\n\n✅ 지하철 6호선 새절역 6분\n✅ 거실 / 방2 / 화장실 / 베란다\n✅ 매매 3억 2천만원\n✅ 초역세권 신축 2룸 오피스텔 찾으시는 분! 바로 여기\n✅ 서부선 예정 / 풀옵션 / 내부상태 최상\n✅ 관리비 10만(추후 변동 가능) / 주차 가능\n✅ 에어컨 / 냉장고 / 세탁기 / 건조기 / 공기전열기 / 인덕션\n\n반려동물 ⭕"
  },
  {
    "중개사_정보": {
      "중개사명": "더원공인중개사사무소",
      "대표자": "양동혁",
      "전화번호": "070-7722-2000",
      "주소": "서울특별시 영등포구 양평동3가 5-4 에이스 하이테크시티3 301호",
      "등록번호": "11560-2025-00096",
      "거래완료": "12건",
      "등록매물": "45건"
    },
    "매물번호": "18419796",
    "매물_URL": "https://www.peterpanz.com/house/18419796",
    "매물_이미지": [
      "https://img.peterpanz.com/photo/20251114/18419796/6916af6bbaac5_origin.jpg",
      "https://img.peterpanz.com/photo/20251114/18419796/6916af6c195d8_origin.jpg",
      "https://img.peterpanz.com/photo/20251114/18419796/6916af6c605e3_origin.jpg",
      "https://img.peterpanz.com/photo/20251114/18419796/6916af6c98030_origin.jpg",
      "https://img.peterpanz.com/photo/20251114/18419796/6916af6cd7aa0_origin.jpg",
      "https://img.peterpanz.com/photo/20251114/18419796/6916af6d221e6_origin.jpg",
      "https://img.peterpanz.com/photo/20251114/18419796/6916af6d612fc_origin.jpg",
      "https://img.peterpanz.com/photo/20251114/18419796/6916af6da5417_origin.jpg",
      "https://img.peterpanz.com/photo/20251114/18419796/6916af6e18b36_origin.jpg",
      "https://img.peterpanz.com/photo/20251114/18419796/6916af6e91893_origin.jpg"
    ],
    "주소_정보": {
      "전체주소": "서울특별시 은평구 신사동 30-51 아줄리움"
    },
    "평면도_URL": [],
    "거래_정보": {
      "거래방식": "월세   3,000만원/120만원",
      "관리비": "관리비 합계 정액 관리비 12만원 공용 관리비 9만원 (정액부과) 사용료 전기 사용량에 따라 별도 부과 수도 사용량에 따라 별도 부과 가스 사용량에 따라 별도 부과 난방 사용량에 따라 별도 부과 인터넷 사용량에 따라 별도 부과 TV 사용량에 따라 별도 부과 기타 관리비 3만원 주차비 관리비 기준: 최근 3개월 관리비 평균금액",
      "융자금": "-",
      "입주가능일": "즉시입주 (협의가능)"
    },
    "매물_정보": {
      "전입신고 여부": "가능",
      "전용/공급면적": "28.81m2/43.82m2 (8.71평/13.25평)",
      "건축물용도": "업무시설",
      "오피스텔명": "아줄리움",
      "동": "1동",
      "해당층/전체층": "7층/11층",
      "방/욕실개수": "2개/1개",
      "방거실형태": "분리형",
      "주실기준/방향": "거실/남서향",
      "현관유형": "계단식",
      "총세대수": "30세대",
      "총주차대수": "17대 (세대당 0.57대)",
      "주차": "가능",
      "사용승인일": "2022.07.29",
      "난방방식": "개별난방",
      "냉방시설": "천장에어컨",
      "생활시설": "냉장고, 세탁기, 싱크대, 가스레인지, 인덕션레인지, 건조기",
      "보안시설": "현관보안, CCTV, 비디오폰, 방범창",
      "기타시설": "화재경보기, 무인택배함, 소화기"
    },
    "추가_옵션": [
      "풀옵션",
      "큰길가",
      "엘리베이터",
      "반려동물",
      "주차가능"
    ],
    "주변_학교": [],
    "상세_설명": "💥허위 매물은 절대 광고하지 않습니다💥\n🏠매물정보🏠\n❤️아주귀한 신축급 풀옵션 투룸월세❤️\n✨ 월세 :3000/120 (보증금 조정가능)\n✨ 옵션: 22년식 신축급 투룸 풀옵션(건조기포함)\n✨ 교통: 6호선 새절역 도보7분(초역세권) , 버스정류장 도보 10초\n✨ 전입.확정일가 가능\n✨ 인프라:한강공원까지 이어지는 불광천 산책로 큰길가앞 치안 안전!\n\n🔹 좋은집, 나에게 맞는집도 중요하지만 “안전한 집”이 가장 우선입니다!\n🔹더이상 허위매물에 속지마세요!\n🔹최대한 원하시는 집 찾아드립니다. 필요조건 알려주시면 몇 일 고생하실 시간 절약!😉\n🔹 월세보다 월 지출이 저렴한 전세 ⚡\n🔹 상담 항목\n1. 대출 : 1금융권 전세자금대출, 무소득자, 프리랜서, 주부, 학생 전세자금 등\n2. 보증보험 : 보증보험,안심전세,중기청,SGI 등\n3. 서류확인 : 등기, 건축물대장, 공제증서 등\n어려워 하시는 부분 100% 성실한 상담 약속 드립니다👍\n\n💌부재 시 혹은 문자 상담 시💌\n'매물번호' 혹은 원하시는 조건을 문자로 남겨주시면 확인 후 바로 연락 드리겠습니다.😊\n\n👍 고객님과의 약속 👍\n🔸 고객님 조건에 맞는 최상의 매물을 찾아드립니다!\n🔹 계약부터 입주까지 끝까지 안전하게 책임!\n🔸 후회없는 선택을 할 수 있도록 도와드리겠습니다!"
  },
  {
    "중개사_정보": {
      "중개사명": "동산이형공인중개사사무소",
      "대표자": "박수빈",
      "전화번호": "010-8113-7780",
      "주소": "서울특별시 마포구 공덕동 467 롯데캐슬프레지던트 24층 오-2403호",
      "등록번호": "11440202500004",
      "거래완료": "1161건",
      "등록매물": "567건"
    },
    "매물번호": "18310868",
    "매물_URL": "https://www.peterpanz.com/house/18310868",
    "매물_이미지": [
      "https://img.peterpanz.com/photo/20251020/18274728/68f5110db446b_origin.jpg",
      "https://img.peterpanz.com/photo/20251020/18274728/68f5110e48d14_origin.jpg",
      "https://img.peterpanz.com/photo/20251020/18274728/68f5110ed85fd_origin.jpg",
      "https://img.peterpanz.com/photo/20251020/18274728/68f5110f5cede_origin.jpg",
      "https://img.peterpanz.com/photo/20251020/18274728/68f5110fde45d_origin.jpg",
      "https://img.peterpanz.com/photo/20251020/18274728/68f51110a0523_origin.jpg",
      "https://img.peterpanz.com/photo/20251020/18274728/68f5111128349_origin.jpg",
      "https://img.peterpanz.com/photo/20251020/18274728/68f51111a493f_origin.jpg",
      "https://img.peterpanz.com/photo/20251020/18274728/68f511126d481_origin.jpg",
      "https://img.peterpanz.com/photo/20251020/18274728/68f51112d5185_origin.jpg",
      "https://img.peterpanz.com/photo/20251020/18274728/68f511136378a_origin.jpg"
    ],
    "주소_정보": {
      "전체주소": "서울특별시 은평구 응암동 577-7 아르지움 주상복합"
    },
    "평면도_URL": [],
    "거래_정보": {
      "거래방식": "매매   2억 6,900만원",
      "관리비": "관리비 확인 불가  미등기건물 신축건물 등 관리비 내역이 확인불가한 경우",
      "융자금": "-",
      "입주가능일": "즉시입주 (협의가능)"
    },
    "매물_정보": {
      "전용/공급면적": "27.96m2/57.89m2 (8.46평/17.51평)",
      "건축물용도": "업무시설",
      "오피스텔명": "아르지움",
      "동": "1동",
      "해당층/전체층": "저층/19층",
      "방/욕실개수": "2개/1개",
      "주실기준/방향": "거실/북서향",
      "현관유형": "복합식",
      "총세대수": "20세대",
      "총주차대수": "106대 (세대당 5.3대)",
      "주차": "가능",
      "사용승인일": "2024.05.16",
      "난방방식": "개별난방",
      "냉방시설": "천장에어컨",
      "생활시설": "냉장고, 세탁기, 싱크대, 신발장, 인덕션레인지",
      "보안시설": "현관보안, CCTV, 인터폰, 비디오폰, 카드키, 자체경비원",
      "기타시설": "화재경보기, 무인택배함, 소화기"
    },
    "추가_옵션": [
      "신축",
      "풀옵션",
      "큰길가",
      "엘리베이터",
      "반려동물",
      "전세자금대출",
      "주차가능"
    ],
    "주변_학교": [],
    "상세_설명": "◈ 100% 직접 방문하여 촬영 된 실 매물\n◈ 허위매물은 취급하지 않습니다\n◈ 서울, 경기도, 인천 전지역,\n기타 외곽지역 매물 다수 보유\n◈ 주차, 엘리베이터 O.K\n◈ 즉시입주, 입주협의\n◈ 특약사항 대출 불가시 계약금 반환 및 꼼꼼체크\n◈ 건축주 분양 & 임대 환영, 부동산 중개,\n개발, 연구 전문 기업\nSJA"
  }
]