[
  {
    "중개사_정보": {},
    "매물번호": "18418730",
    "매물_URL": "https://www.peterpanz.com/house/18418730",
    "매물_이미지": [
      "https://img.peterpanz.com/photo/20250120/16809459/7c8cf0b23c86dbfb9d54fcae528bd4de_origin.jpg",
      "https://img.peterpanz.com/photo/20250120/16809459/203a571d0089826c6a23a558000002f7_origin.jpg",
      "https://img.peterpanz.com/photo/20250120/16809459/97281b3efe7ec8ad5f65f45f8f05eb72_origin.jpg",
      "https://img.peterpanz.com/photo/20250120/16809459/9b1569f048e60a9f9fb78bfe4c88d8eb_origin.jpg",
      "https://img.peterpanz.com/photo/20250120/16809459/64604a3596880742635be9f7900bd87c_origin.jpg",
      "https://img.peterpanz.com/photo/20250120/16809459/eab6c26fce5b8aa996c763bc84cd36ca_origin.jpg",
      "https://img.peterpanz.com/photo/20250512/17495439/c277e17dae48bd4c7532188e07b27541_origin.jpg",
      "https://img.peterpanz.com/photo/20250512/17495439/94cbb7d7063e1baf9c747cdc802cd634_origin.jpg",
      "https://img.peterpanz.com/photo/20250512/17495439/e837195c7792b95fd1746cf9e434d3e9_origin.jpg",
      "https://img.peterpanz.com/photo/20250512/17495439/937c437f628517208a683492cab2c9d6_origin.jpg",
      "https://img.peterpanz.com/photo/20250512/17495439/765967c647c7dc6886053764445d1f49_origin.jpg"
    ],
    "주소_정보": {
      "전체주소": "서울특별시 용산구 한남동"
    },
    "평면도_URL": [],
    "거래_정보": {
      "거래방식": "월세   1,000만원/110만원",
      "관리비": "없음 관리비 별도 난방, 전기, 수도",
      "융자금": "융자금 없음",
      "입주가능일": "즉시입주 (협의가능)"
    },
    "매물_정보": {
      "건축물용도": "제1종 근린생활시설",
      "건물형태": "중소형사무실",
      "전용/계약면적": "19.83m2/19.83m2 (6평/6평)",
      "해당층/전체층": "1층/3층",
      "점포(사무실)개수": "1개",
      "화장실개수": "1개",
      "주된출입구": "서향",
      "총주차대수": "0대",
      "주차": "불가",
      "위반건축물 여부": "-",
      "사용승인일": "1976.01.01",
      "난방방식": "개별난방",
      "냉방시설": "벽걸이에어컨",
      "보안시설": "CCTV",
      "기타시설": "-"
    },
    "추가_옵션": [],
    "주변_학교": [],
    "상세_설명": "현재 파티룸으로 운영중입니다\n사이즈는 7평남짓이지만 공간이 길게 빠져있어 충분히 넓게 사용중입니다. 화장실 실내에 있습니다\n같은 업종으로 하셔도 되고 공방이나 타투샵 사무실 꽃집 악세사리 등\n다양하게 업종 선택가능할듯 싶습니다\n\n저도 전 세입자도 사무실겸 파티룸으로 운영해온바 매달 월세 이상의 수입은 나옵니다.\n\n바로 앞 편의점 /한남오거리 도보 3분/한남역 도보 4분/한강으로가는길목/브라이튼한남 등등\n상권이 좋아요 \n다만 음식점이나 카페 술집은 어렵습니다\n임대인분께서 원하지 않아하십니다.\n권리금 있습니다.\n관심있으신분들 연락 많이주세요\n\n***월세 5프로 인상 예정입니다 참고해주세요\n\n매달 월세에 부가세 10프로 함께내야합니다\n세금계산서 요청하시면 됩니다"
  },
  {
    "중개사_정보": {},
    "매물번호": "18367055",
    "매물_URL": "https://www.peterpanz.com/house/18367055",
    "매물_이미지": [
      "https://img.peterpanz.com/photo/20251105/18367055/fb2a2c9c8026a44cebd06b1f9cfb59c2_origin.jpg",
      "https://img.peterpanz.com/photo/20251105/18367055/91eb8414b347eb4b8806035b5f81407d_origin.jpg"
    ],
    "주소_정보": {
      "전체주소": "서울특별시 용산구 한남동"
    },
    "평면도_URL": [],
    "거래_정보": {
      "거래방식": "월세   4,000만원/390만원",
      "관리비": "없음",
      "입주가능일": "2025. 11. 05. 이후 (협의가능)"
    },
    "매물_정보": {
      "건물형태": "상가/사무실",
      "건물명": "대영빌딩",
      "전용/계약면적": "125.63m2/125.63m2 (38평/38평)",
      "해당층/전체층": "2층/5층",
      "점포(사무실)개수": "2개",
      "화장실개수": "0개",
      "주차": "가능",
      "위반건축물 여부": "-",
      "난방방식": "개별난방",
      "냉방시설": "-",
      "보안시설": "-",
      "기타시설": "-"
    },
    "추가_옵션": [],
    "주변_학교": [],
    "상세_설명": "\"감각적인 인테리어의 하이엔드 한남동 오피스\" 한남동 유엔빌리지 근처/ 스타벅스 R점 바로 옆에 위치한 세련된 사무실 입니다. ​ 고급 자재로 완성된 인테리어와 브랜드 이미지를 돋보이게 할 감각적인 구조가 특징이고, 햇살이 잘 들어와 쾌적하고, 트렌디한 한남동의 분위기를 그대로 담은 공간입니다. ​ 특히, 화장품 브랜드 · 패션 회사 · 크리에이티브 기업에 이상적이며, 브랜드의 격을 높여줄 프리미엄 오피스입니다. ​ 공간 포인트 고급 자재 & 세련된 인테리어 (바로 입주 가능) 한남동 핵심 입지, 트렌디한 상권 중심 브랜드 사무실, 쇼룸, 크리에이티브 스튜디오로 최적화 ​ ​ ​"
  },
  {
    "중개사_정보": {},
    "매물번호": "18435519",
    "매물_URL": "https://www.peterpanz.com/house/18435519",
    "매물_이미지": [
      "https://img.peterpanz.com/photo/20251117/18435519/691ac3d5520ce_origin.jpg",
      "https://img.peterpanz.com/photo/20251117/18435519/691ac3d5cb15a_origin.jpg",
      "https://img.peterpanz.com/photo/20251117/18435519/691ac3d654d52_origin.jpg",
      "https://img.peterpanz.com/photo/20251117/18435519/691ac3d6cf803_origin.jpg",
      "https://img.peterpanz.com/photo/20251117/18435519/691ac3d74c860_origin.jpg",
      "https://img.peterpanz.com/photo/20251117/18435519/691ac3d7bbc56_origin.jpg",
      "https://img.peterpanz.com/photo/20251117/18435519/691ac3d84e631_origin.jpg",
      "https://img.peterpanz.com/photo/20251117/18435519/691ac3d903170_origin.jpg",
      "https://img.peterpanz.com/photo/20251117/18435519/691ac3d967227_origin.jpg",
      "https://img.peterpanz.com/photo/20251117/18435519/691ac3d9c67c2_origin.jpg",
      "https://img.peterpanz.com/photo/20251117/18435519/691ac3da4043e_origin.jpg",
      "https://img.peterpanz.com/photo/20251117/18435519/691ac3dabc416_origin.jpg",
      "https://img.peterpanz.com/photo/20251117/18435519/691ac3db384cd_origin.jpg",
      "https://img.peterpanz.com/photo/20251117/18435519/691ac3dbcd6fa_origin.jpg",
      "https://img.peterpanz.com/photo/20251117/18435519/691ac3dc685ef_origin.jpg"
    ],
    "주소_정보": {
      "전체주소": "서울특별시 강남구 신사동"
    },
    "평면도_URL": [],
    "거래_정보": {
      "거래방식": "월세   1억/1,400만원",
      "관리비": "100만원 관리비 별도 전기, 가스, 수도",
      "융자금": "융자금 없음",
      "입주가능일": "즉시입주 (협의가능)"
    },
    "매물_정보": {
      "건축물용도": "판매시설",
      "건물형태": "일반상가",
      "전용/계약면적": "132.24m2/152.08m2 (40평/46평)",
      "해당층/전체층": "1층/3층",
      "점포(사무실)개수": "1개",
      "화장실개수": "1개",
      "주된출입구": "동향",
      "총주차대수": "0대",
      "주차": "불가",
      "위반건축물 여부": "위반건축물 아님",
      "사용승인일": "2010"
    },
    "추가_옵션": [],
    "주변_학교": [],
    "상세_설명": "압구정로데오 5번출구쪽 먹자골목에 위치한 상가 입니다.\n권리금 조정 가능하며, 압구정로데오 메인거리에 위치해 있어 유동인구가 활발 합니다.\n언제든지 문의 편하게 문의 주세요!"
  },
  {
    "중개사_정보": {
      "중개사명": "주식회사더탑원부동산중개법인",
      "대표자": "서문교",
      "전화번호": "02-555-2297",
      "주소": "서울특별시 강남구 언주로 331 2층 202호",
      "등록번호": "11680-2024-00304",
      "거래완료": "1388건",
      "등록매물": "114건"
    },
    "매물번호": "18357258",
    "매물_URL": "https://www.peterpanz.com/house/18357258",
    "매물_이미지": [
      "https://img.peterpanz.com/photo/20251103/18355328/690831711e441_origin.jpg",
      "https://img.peterpanz.com/photo/20251103/18355328/690831719937a_origin.jpg",
      "https://img.peterpanz.com/photo/20251103/18355328/6908317216cdb_origin.jpg",
      "https://img.peterpanz.com/photo/20251103/18355328/6908317281717_origin.jpg",
      "https://img.peterpanz.com/photo/20251103/18355328/69083172e426f_origin.jpg"
    ],
    "주소_정보": {
      "전체주소": "서울특별시 강남구 청담동"
    },
    "평면도_URL": [],
    "거래_정보": {
      "거래방식": "월세   1억 5,000만원/800만원",
      "관리비": "80만원 관리비 별도 전기, 가스, 수도, 난방",
      "융자금": "-",
      "입주가능일": "즉시입주"
    },
    "매물_정보": {
      "건축물용도": "제1종 근린생활시설",
      "건물형태": "일반상가",
      "전용/계약면적": "158.25m2/263.25m2 (47.87평/79.63평)",
      "해당층/전체층": "1층/5층",
      "점포(사무실)개수": "0개",
      "화장실개수": "1개",
      "주된출입구": "남동향",
      "총주차대수": "12대",
      "주차": "가능",
      "위반건축물 여부": "위반건축물 아님",
      "사용승인일": "1992.11.21"
    },
    "추가_옵션": [
      "주차가능"
    ],
    "주변_학교": [],
    "상세_설명": "📌 English Available.\n\n🏢더탑원부동산중개법인🏢\n\n유선문의시 원하시는 조건에 맞는 자료와 차별화된 서비스로\n최고의 임차조건 Rent-Free, Fit-Out,Tenant Improvement\n경험하시길 바랍니다. 📞\n\n👩🏻‍💼［매물 소개 ]👨🏻‍💼\n\n✅ 오늘자 원복 완료될 예정\n✅ 관리 잘 되어 컨디션 GOOD\n✅ 즉시입주 가능\n✅ 주차 : 가능\n✅ 유동인구 많은 위치\n✅ 위반건축물X\n✅ 계약면적은 건축물대장상 면적을 기준으로 작성되었으며, 해당층 일부를 사용함에 따라, 계약면적과 전용면적은 실제, 계약서상 면적과 상이할 수 있습니다.\n\n\n< 광고하지 못하는 다양한 매물들 보유중입니다>\n___________________________________________________________\n\n『융자금의 경우 등기부등본 확인 후 기재한 내용이 아니라서 실제와 다름이 있을 수 있으나,\n계약 진행 전 또는 문의하시면 등기부등본 확인 후 정확한 설명드리겠습니다』\n\n중개사 추천 : 계약 전 '세이프홈즈' 확인! 당신의 전세보증금을 지키는 가장 확실한 방법입니다."
  },
  {
    "중개사_정보": {
      "중개사명": "주식회사더탑원부동산중개법인",
      "대표자": "서문교",
      "전화번호": "02-555-2297",
      "주소": "서울특별시 강남구 언주로 331 2층 202호",
      "등록번호": "11680-2024-00304",
      "거래완료": "1388건",
      "등록매물": "114건"
    },
    "매물번호": "18380454",
    "매물_URL": "https://www.peterpanz.com/house/18380454",
    "매물_이미지": [
      "https://img.peterpanz.com/photo/20251107/18380454/690d641413e18_origin.jpg",
      "https://img.peterpanz.com/photo/20251107/18380454/690d641488f93_origin.jpg",
      "https://img.peterpanz.com/photo/20251107/18380454/690d6414d10c1_origin.jpg",
      "https://img.peterpanz.com/photo/20251107/18380454/690d641519a15_origin.jpg",
      "https://img.peterpanz.com/photo/20251107/18380454/690d64154df22_origin.jpg",
      "https://img.peterpanz.com/photo/20251107/18380454/690d641587e37_origin.jpg",
      "https://img.peterpanz.com/photo/20251107/18380454/690d6415c4c8b_origin.jpg"
    ],
    "주소_정보": {
      "전체주소": "서울특별시 강남구 청담동"
    },
    "평면도_URL": [],
    "거래_정보": {
      "거래방식": "월세   2억/1,300만원",
      "관리비": "200만원 관리비 별도 전기, 가스, 수도, 난방",
      "융자금": "-",
      "입주가능일": "즉시입주"
    },
    "매물_정보": {
      "건축물용도": "업무시설",
      "건물형태": "중소형사무실",
      "전용/계약면적": "273.6m2/329.7m2 (82.76평/99.73평)",
      "해당층/전체층": "3층/5층",
      "점포(사무실)개수": "0개",
      "화장실개수": "2개",
      "주된출입구": "남서향",
      "총주차대수": "12대",
      "주차": "가능",
      "위반건축물 여부": "-",
      "사용승인일": "1992.11.21"
    },
    "추가_옵션": [
      "주차가능"
    ],
    "주변_학교": [],
    "상세_설명": "📌 English Available.\n\n🏢더탑원부동산중개법인🏢\n\n유선문의시 원하시는 조건에 맞는 자료와 차별화된 서비스로\n최고의 임차조건 Rent-Free, Fit-Out,Tenant Improvement\n경험하시길 바랍니다. 📞\n\n👩🏻‍💼［매물 소개 ]👨🏻‍💼\n\n✅ 하이앤드 상권내 최상 입지 컨디션\n✅ 관리 잘 되어 컨디션 GOOD\n✅ 즉시입주 가능\n✅ 주차 : 가능\n✅ 유동인구 많은 위치\n✅ 위반건축물 X\n\n\n< 광고하지 못하는 다양한 매물들 보유중입니다>\n___________________________________________________________\n\n『융자금의 경우 등기부등본 확인 후 기재한 내용이 아니라서 실제와 다름이 있을 수 있으나,\n계약 진행 전 또는 문의하시면 등기부등본 확인 후 정확한 설명드리겠습니다』\n\n중개사 추천 : 계약 전 '세이프홈즈' 확인! 당신의 전세보증금을 지키는 가장 확실한 방법입니다."
  },
  {
    "중개사_정보": {
      "중개사명": "더라움공인중개사사무소",
      "대표자": "김민우",
      "전화번호": "02-564-3999",
      "주소": "서울특별시 강남구 학동로8길 10 506호(논현동,은솔빌딩)",
      "등록번호": "11680-2021-00138",
      "거래완료": "8건",
      "등록매물": "521건"
    },
    "매물번호": "18319647",
    "매물_URL": "https://www.peterpanz.com/house/18319647",
    "매물_이미지": [
      "https://img.peterpanz.com/photo/20250328/17224646/67f38be75df14_origin.jpg",
      "https://img.peterpanz.com/photo/20250328/17224646/67f38be807389_origin.jpg",
      "https://img.peterpanz.com/photo/20250328/17224646/67f38be88904a_origin.jpg",
      "https://img.peterpanz.com/photo/20250328/17224646/67f38be9057c7_origin.jpg",
      "https://img.peterpanz.com/photo/20250328/17224646/67f38be98bbb2_origin.jpg",
      "https://img.peterpanz.com/photo/20250328/17224646/67f38be9ed3a8_origin.jpg",
      "https://img.peterpanz.com/photo/20250328/17224646/67f38bea697b9_origin.jpg",
      "https://img.peterpanz.com/photo/20250328/17224646/67f38beae4066_origin.jpg",
      "https://img.peterpanz.com/photo/20250328/17224646/67f38beb67dd8_origin.jpg",
      "https://img.peterpanz.com/photo/20250328/17224646/67f38bebd8f59_origin.jpg",
      "https://img.peterpanz.com/photo/20250328/17224646/67f38bec5670f_origin.jpg",
      "https://img.peterpanz.com/photo/20250328/17224646/67f38beccc476_origin.jpg",
      "https://img.peterpanz.com/photo/20250328/17224646/67f38bed5add8_origin.jpg"
    ],
    "주소_정보": {
      "전체주소": "서울특별시 강남구 청담동"
    },
    "평면도_URL": [],
    "거래_정보": {
      "거래방식": "월세   1,100만원/240만원",
      "관리비": "30만원 수도 관리비 별도 전기, 가스, 난방",
      "융자금": "-",
      "입주가능일": "2025. 11. 16. 이후 (협의가능)"
    },
    "매물_정보": {
      "건축물용도": "제1종 근린생활시설",
      "건물형태": "중소형사무실",
      "건물명": "청담아이파크",
      "전용/계약면적": "61.28m2/61.28m2 (18.54평/18.54평)",
      "해당층/전체층": "3층/19층",
      "점포(사무실)개수": "1개",
      "화장실개수": "1개",
      "주된출입구": "동향",
      "총주차대수": "129대",
      "주차": "가능",
      "위반건축물 여부": "위반건축물 아님",
      "사용승인일": "1992.10.28",
      "난방방식": "개별난방",
      "냉방시설": "천장에어컨",
      "보안시설": "-",
      "기타시설": "-"
    },
    "추가_옵션": [
      "풀옵션",
      "엘리베이터",
      "주차가능"
    ],
    "주변_학교": [],
    "상세_설명": "================================\n\n“성실하고 정직한 중개를 약속합니다.”\n\n✅ THE라움 공인중개사사무소 ✅\n\n================================\n\n📌 12개월 이상 자유롭게 계약 가능 (한달씩 연장 OK)\n\n================================\n\n◎ 인테리어 완비된 차원이 다른 단독 풀옵션\n\n◎ 한개 층 단독 사용 풀옵션 오피스\n\n◎ 가전, 가구 및 사무집기 셋팅 협의가능\n\n================================\n\n📌 단기임대도 가능합니다.\n\n================================\n\n◆수수료 없는 카드결제 가능\n\n◆내부 럭셔리 올 리모델링\n\n◆고급 책상, 의자, 소파, 테이블 풀옵션\n\n◆홀, 룸 전체 냉난방기 설치완료\n\n◆인터넷, 정수기, 냉장고 구비완료\n\n◆사업자등록 및 세금계산서 모두 가능\n\n================================\n\n✅ THE라움 공인중개사사무소 ✅\n\n☎️ 0 1 0 - 3 4 4 2 - 4 5 6 4\n\n☎️ 카카오톡ID: minu41"
  },
  {
    "중개사_정보": {
      "중개사명": "더라움공인중개사사무소",
      "대표자": "김민우",
      "전화번호": "02-564-3999",
      "주소": "서울특별시 강남구 학동로8길 10 506호(논현동,은솔빌딩)",
      "등록번호": "11680-2021-00138",
      "거래완료": "8건",
      "등록매물": "521건"
    },
    "매물번호": "18424635",
    "매물_URL": "https://www.peterpanz.com/house/18424635",
    "매물_이미지": [
      "https://img.peterpanz.com/photo/20241231/16672712/678633a9d2017_origin.jpg",
      "https://img.peterpanz.com/photo/20241231/16672712/678633aa6e70f_origin.jpg",
      "https://img.peterpanz.com/photo/20241231/16672712/678633ab00a2c_origin.jpg",
      "https://img.peterpanz.com/photo/20241231/16672712/678633ab7db97_origin.jpg",
      "https://img.peterpanz.com/photo/20241231/16672712/678633ac0a261_origin.jpg",
      "https://img.peterpanz.com/photo/20241231/16672712/678633ac7f876_origin.jpg",
      "https://img.peterpanz.com/photo/20241231/16672712/678633ad13e9e_origin.jpg",
      "https://img.peterpanz.com/photo/20241231/16672712/678633ad96697_origin.jpg",
      "https://img.peterpanz.com/photo/20241231/16672712/678633ae3184c_origin.jpg",
      "https://img.peterpanz.com/photo/20241231/16672712/678633aeabcca_origin.jpg",
      "https://img.peterpanz.com/photo/20241231/16672712/678633af44618_origin.jpg",
      "https://img.peterpanz.com/photo/20241231/16672712/678633afc6864_origin.jpg",
      "https://img.peterpanz.com/photo/20241231/16672712/678633b03f54f_origin.jpg",
      "https://img.peterpanz.com/photo/20241231/16672712/678633b0bd9a4_origin.jpg",
      "https://img.peterpanz.com/photo/20241231/16672712/678633b14e3ea_origin.jpg"
    ],
    "주소_정보": {
      "전체주소": "서울특별시 강남구 청담동"
    },
    "평면도_URL": [],
    "거래_정보": {
      "거래방식": "단기임대   170만원/281만원",
      "관리비": "없음 관리비 별도 전기, 가스, 난방",
      "융자금": "-",
      "입주가능일": "2025. 11. 16. 이후 (협의가능)"
    },
    "매물_정보": {
      "계약기간": "2025. 11. 15. ~ 2026. 11. 16.",
      "건축물용도": "제1종 근린생활시설",
      "건물형태": "중소형사무실",
      "건물명": "청담아이파크",
      "전용/계약면적": "61.28m2/61.28m2 (18.54평/18.54평)",
      "해당층/전체층": "3층/19층",
      "점포(사무실)개수": "1개",
      "화장실개수": "1개",
      "주된출입구": "동향",
      "총주차대수": "129대",
      "주차": "가능",
      "위반건축물 여부": "위반건축물 아님",
      "사용승인일": "1992.10.28",
      "난방방식": "개별난방",
      "냉방시설": "천장에어컨",
      "보안시설": "-",
      "기타시설": "-"
    },
    "추가_옵션": [
      "풀옵션",
      "엘리베이터",
      "주차가능"
    ],
    "주변_학교": [],
    "상세_설명": "================================\n\n✅ 모든 호실 할인 이벤트중 ✅\n\n================================\n\n◎ 인테리어 완비된 차원이 다른 단독 풀옵션\n\n◎ 한개 층 단독 사용 풀옵션 오피스\n\n◎ 가전, 가구 및 사무집기 셋팅 협의가능\n\n================================\n\n\n📌1개월 월세 금액입니다~\n📌1개월부터 자유롭게 계약 가능합니다~\n(계약기간에 따라 금액 변동 있을 수 있습니다)\n\n\n================================\n\n◆수수료 없는 카드결제 가능!\n\n◆관리비, 수도, 정수기, 인터넷 사용료 포함\n\n◆내부 럭셔리 올 리모델링\n\n◆고급 책상, 의자, 소파, 테이블 풀옵션\n\n◆홀, 룸 전체 개별 냉난방기 설치완료\n\n◆인터넷, 정수기, 냉장고, 전자레인지 기본옵션\n\n◆사업자등록 및 세금계산서 모두 가능\n\n================================"
  },
  {
    "중개사_정보": {},
    "매물번호": "18384982",
    "매물_URL": "https://www.peterpanz.com/house/18384982",
    "매물_이미지": [
      "https://img.peterpanz.com/photo/20251108/18384982/008648f468c513885b5b4f9f56f35355_origin.jpg",
      "https://img.peterpanz.com/photo/20251108/18384982/cc1b9799549a24bed49e2cc6298ffec8_origin.jpg",
      "https://img.peterpanz.com/photo/20251108/18384982/950c406c1a0acf76fe624b962f7a072a_origin.jpg",
      "https://img.peterpanz.com/photo/20251108/18384982/e98c98816f065036b3a203adcad9722b_origin.jpg",
      "https://img.peterpanz.com/photo/20251108/18384982/7f841f0ddce9b408e6b55169fe17f238_origin.jpg",
      "https://img.peterpanz.com/photo/20251108/18384982/58adb2fde4c7692e0bf2663ae150ffb7_origin.jpg",
      "https://img.peterpanz.com/photo/20251108/18384982/4cee27d1f9d52310b1cd85da7791c830_origin.jpg",
      "https://img.peterpanz.com/photo/20251108/18384982/008173a7dba4e24ae9fac34ca8f17c9b_origin.jpg",
      "https://img.peterpanz.com/photo/20251108/18384982/25d74ada6b6768ffbeaa3e1361dea899_origin.jpg",
      "https://img.peterpanz.com/photo/20251108/18384982/ee6cde1e8376e01c7aae54a462e09d54_origin.jpg",
      "https://img.peterpanz.com/photo/20251108/18384982/5f0ef18047598c53ae190bbdaaa5b0bf_origin.jpg"
    ],
    "주소_정보": {
      "전체주소": "서울특별시 성동구 성수동1가"
    },
    "평면도_URL": [],
    "거래_정보": {
      "거래방식": "월세   3,000만원/230만원",
      "관리비": "20만원 관리비 별도 난방, 전기, 수도, 가스",
      "융자금": "융자금 없음",
      "입주가능일": "2025. 12. 01. 이후 (협의가능)"
    },
    "매물_정보": {
      "건축물용도": "제2종 근린생활시설",
      "건물형태": "일반상가",
      "전용/계약면적": "105.14m2/105.17m2 (31.8평/31.81평)",
      "해당층/전체층": "3층/4층",
      "점포(사무실)개수": "2개",
      "화장실개수": "2개",
      "주된출입구": "동향",
      "총주차대수": "0대",
      "주차": "불가",
      "위반건축물 여부": "위반건축물 아님",
      "사용승인일": "1987.08.08",
      "난방방식": "개별난방",
      "냉방시설": "천장에어컨",
      "보안시설": "현관보안, CCTV",
      "기타시설": "베란다"
    },
    "추가_옵션": [],
    "주변_학교": [],
    "상세_설명": "서울숲 이용 5분 거리, 매장 내 서울숲 조망권 확보, 성동구민종합체육센터 버스 정류장 앞 피리바게트 건물, 유동 인구 최다"
  },
  {
    "중개사_정보": {},
    "매물번호": "18387950",
    "매물_URL": "https://www.peterpanz.com/house/18387950",
    "매물_이미지": [
      "https://img.peterpanz.com/photo/20250924/18152836/68d5ca4489c9de8f020360525e45f27a_origin.jpg",
      "https://img.peterpanz.com/photo/20250924/18152836/aa47f1ff69552f0b6a647a3833445094_origin.jpg",
      "https://img.peterpanz.com/photo/20251109/18387950/69185915b6fd0_origin.jpg",
      "https://img.peterpanz.com/photo/20251109/18387950/6918591666d91_origin.jpg",
      "https://img.peterpanz.com/photo/20251109/18387950/691859173b4f0_origin.jpg",
      "https://img.peterpanz.com/photo/20251109/18387950/691859182204d_origin.jpg",
      "https://img.peterpanz.com/photo/20251109/18387950/691859190f00e_origin.jpg",
      "https://img.peterpanz.com/photo/20251109/18387950/69185919c6aa2_origin.jpg",
      "https://img.peterpanz.com/photo/20251109/18387950/6918591a7c7c7_origin.jpg",
      "https://img.peterpanz.com/photo/20251109/18387950/6918591b3a47d_origin.jpg",
      "https://img.peterpanz.com/photo/20251109/18387950/6918591beb505_origin.jpg"
    ],
    "주소_정보": {
      "전체주소": "서울특별시 성동구 성수동1가"
    },
    "평면도_URL": [],
    "거래_정보": {
      "거래방식": "월세   2,000만원/160만원",
      "관리비": "5만원 수도 관리비 별도 전기, 난방",
      "융자금": "-",
      "입주가능일": "즉시입주"
    },
    "매물_정보": {
      "건축물용도": "업무시설",
      "건물형태": "중소형사무실",
      "전용/계약면적": "38.24m2/38.24m2 (11.57평/11.57평)",
      "해당층/전체층": "3층/3층",
      "점포(사무실)개수": "1개",
      "화장실개수": "1개",
      "주된출입구": "북동향",
      "총주차대수": "1대",
      "주차": "가능",
      "위반건축물 여부": "위반건축물 아님",
      "사용승인일": "1994.04.05",
      "난방방식": "개별난방",
      "냉방시설": "벽걸이에어컨",
      "보안시설": "-",
      "기타시설": "-"
    },
    "추가_옵션": [
      "주차가능"
    ],
    "주변_학교": [],
    "상세_설명": "서울숲 근방의 단독 건물입니다. 1층에 유명 편집샵이 있을만큼 외관이 예쁘고 해가 하루종일 잘 들어오는 예쁜 사무실이에요. 제가 도어락 등 설치해뒀으며 개별 에어컨 새것 있습니다. 단독 사무실 쓰시기 좋아요. 물류 계약 때문에 급히 나가는 것이라, 필요시에 기물들( 보관랙, 책상 등) 두고 나갈 수 있어요. 옥상도 함께 써서 보관 물품도 많이 들어가요!\n첫달 렌트프리입니다"
  },
  {
    "중개사_정보": {},
    "매물번호": "18249294",
    "매물_URL": "https://www.peterpanz.com/house/18249294",
    "매물_이미지": [
      "https://img.peterpanz.com/photo/20251015/18249294/68eef67a3bf9a_origin.jpg",
      "https://img.peterpanz.com/photo/20251015/18249294/68eef67ac7a32_origin.jpg",
      "https://img.peterpanz.com/photo/20251015/18249294/68eef67b6668f_origin.jpg"
    ],
    "주소_정보": {
      "전체주소": "서울특별시 성동구 성수동1가"
    },
    "평면도_URL": [],
    "거래_정보": {
      "거래방식": "월세   1,700만원/170만원",
      "관리비": "20만원 전기, 수도",
      "융자금": "-",
      "입주가능일": "즉시입주 (협의가능)"
    },
    "매물_정보": {
      "건축물용도": "공장",
      "건물형태": "중소형사무실",
      "전용/계약면적": "44.1m2/90.7m2 (13.34평/27.43평)",
      "해당층/전체층": "9층/12층",
      "점포(사무실)개수": "1개",
      "화장실개수": "1개",
      "주된출입구": "남동향",
      "총주차대수": "128대",
      "주차": "가능",
      "위반건축물 여부": "위반건축물 아님",
      "사용승인일": "2025.01.08",
      "난방방식": "개별난방",
      "냉방시설": "천장에어컨",
      "보안시설": "-",
      "기타시설": "테라스, 소화기"
    },
    "추가_옵션": [
      "주차가능"
    ],
    "주변_학교": [],
    "상세_설명": "임대차 조건 1700/170만원\n전용면적 13 + 발코니면적 별도 = 실사용 15평\n해당층 9층 (총12층)\n관리비 20만원 내외\nE/V 승객용(4대) + 화물용(1대)\n신축 후 첫 입주.\n\n신축 지식산업센터, 최적의 업무환경\n서울숲역(수인분당선), 뚝섬역(2호선) 사이 위치. 더블역세권.\n발코니 면적 활용가능.\n시스템 냉난방기 설치."
  },
  {
    "중개사_정보": {
      "중개사명": "강남ON공인중개사사무소",
      "대표자": "임태호",
      "전화번호": "02-6949-2300",
      "주소": "서울특별시 강남구 선릉로121길 7 2층",
      "등록번호": "11680-2021-00168",
      "거래완료": "1769건",
      "등록매물": "72건"
    },
    "매물번호": "18310963",
    "매물_URL": "https://www.peterpanz.com/house/18310963",
    "매물_이미지": [
      "https://img.peterpanz.com/photo/20250815/17934896/689f2060b002c_origin.jpg",
      "https://img.peterpanz.com/photo/20250815/17934896/689f2061264df_origin.jpg",
      "https://img.peterpanz.com/photo/20250815/17934896/689f20618dc8e_origin.jpg",
      "https://img.peterpanz.com/photo/20250815/17934896/689f20621d71f_origin.jpg",
      "https://img.peterpanz.com/photo/20250815/17934896/689f206289075_origin.jpg",
      "https://img.peterpanz.com/photo/20250815/17934896/689f2062e464f_origin.jpg",
      "https://img.peterpanz.com/photo/20250815/17934896/689f20634fa57_origin.jpg",
      "https://img.peterpanz.com/photo/20250815/17934896/689f2063bb792_origin.jpg"
    ],
    "주소_정보": {
      "전체주소": "서울특별시 성동구 성수동1가"
    },
    "평면도_URL": [],
    "거래_정보": {
      "거래방식": "월세   2,000만원/190만원",
      "관리비": "없음 관리비 별도 난방, 전기, 수도, 가스",
      "융자금": "-",
      "입주가능일": "즉시입주 (협의가능)"
    },
    "매물_정보": {
      "건축물용도": "제2종 근린생활시설",
      "건물형태": "중소형사무실",
      "전용/계약면적": "59.36m2/109m2 (17.96평/32.97평)",
      "해당층/전체층": "3층/3층",
      "점포(사무실)개수": "1개",
      "화장실개수": "1개",
      "주된출입구": "동향",
      "총주차대수": "0대",
      "주차": "불가",
      "위반건축물 여부": "-",
      "사용승인일": "1991.02.06",
      "난방방식": "개별난방",
      "냉방시설": "천장에어컨",
      "보안시설": "-",
      "기타시설": "테라스"
    },
    "추가_옵션": [],
    "주변_학교": [],
    "상세_설명": "─ 강남ON부동산 ────────────\n\n임차 전속 부동산입니다.\n스튜디오, 뷰티업종 등 다양한 업종 문의 가능하며,\n채광과 층고가 뛰어납니다.\n\n*본 물건은 소정의 권리금이 존재합니다. (협의가능)\n\n\n━━━━━━▣ 매물 설명 ▣━━━━━━\n\n■ 대수선하여 신축급 건물\n\n■ 인테리어 및 시설 완비\n\n■ 내부 화장실\n\n■ 높은 층고 와 소형테라스\n\n■ 관리비 : 실비\n\n\n\n━━━━━▣ 강남ON부동산 ▣━━━━━\n\n■ 모든 거래에 대한 권리 분석 까지 진행\n\n■ 각종 대출 상담 환영\n\n■ 중개 사고 없는 부동산"
  },
  {
    "중개사_정보": {},
    "매물번호": "18312635",
    "매물_URL": "https://www.peterpanz.com/house/18312635",
    "매물_이미지": [
      "https://img.peterpanz.com/photo/20250605/17643993/4a7a3e26e88b3fd7c9936f0307497cba_origin.jpg",
      "https://img.peterpanz.com/photo/20250605/17643993/7f6333d5564a7144267627d759546181_origin.jpg",
      "https://img.peterpanz.com/photo/20250605/17643993/794827614226f4466bf609062704216a_origin.jpg",
      "https://img.peterpanz.com/photo/20250605/17643993/aea2e9837a0e204838a1c1ef75dae8f6_origin.jpg",
      "https://img.peterpanz.com/photo/20250605/17643993/77351ee2507374ffdedd20a38ed95c3f_origin.jpg"
    ],
    "주소_정보": {
      "전체주소": "서울특별시 성동구 성수동1가"
    },
    "평면도_URL": [],
    "거래_정보": {
      "거래방식": "매매   65억",
      "관리비": "없음",
      "융자금": "7억 5,000만원 (시세 대비 30% 미만)",
      "입주가능일": "즉시입주 (협의가능)"
    },
    "매물_정보": {
      "건축물용도": "제2종 근린생활시설",
      "건물형태": "중소형사무실",
      "전용/계약면적": "198.24m2/198.24m2 (59.96평/59.96평)",
      "해당층/전체층": "4층/4층",
      "점포(사무실)개수": "4개",
      "화장실개수": "3개",
      "주된출입구": "동향",
      "총주차대수": "1대",
      "주차": "가능",
      "위반건축물 여부": "위반건축물 아님",
      "사용승인일": "2020.01.29",
      "난방방식": "-",
      "냉방시설": "천장에어컨",
      "보안시설": "-",
      "기타시설": "-"
    },
    "추가_옵션": [
      "주차가능"
    ],
    "주변_학교": [],
    "상세_설명": "면적 : 연면적 60평 / 대지 36평\n해당층/총층 : 전체/B1~3층\n주차 : 1대\n\n-깔끔하고 모던한 신축 매물\n-서울숲 아뜰리에 상권\n-분당선 서울숲역, 2호선 뚝섬역\n-2020년 준공, 최상의 건물 상태\n-높은 층고\n-갤러리아포레, 아크로포레스트 등 고급주거복합단지\n-SM엔터 사옥 인접\n-성수대교,영동대교, 강변북로 이용 강남 10분대\n-시스템 냉난방기 완비"
  },
  {
    "중개사_정보": {
      "중개사명": "에이원공인중개사사무소",
      "대표자": "김도윤",
      "전화번호": "02-749-5355",
      "주소": "서울특별시 용산구 이태원동 207-6 에이원에비뉴 1층",
      "등록번호": "11170201700002",
      "거래완료": "46건",
      "등록매물": "5건"
    },
    "매물번호": "18366796",
    "매물_URL": "https://www.peterpanz.com/house/18366796",
    "매물_이미지": [],
    "주소_정보": {
      "전체주소": "서울특별시 성동구 성수동2가"
    },
    "평면도_URL": [],
    "거래_정보": {
      "거래방식": "매매   246억",
      "관리비": "없음",
      "융자금": "-",
      "입주가능일": "즉시입주 (협의가능)"
    },
    "매물_정보": {
      "건축물용도": "제2종 근린생활시설",
      "건물형태": "빌딩",
      "세부종류": "빌딩",
      "건물명": "성수빌딩",
      "건축구조": "철골조",
      "용도지역": "준공업지역",
      "현재용도": "근린생활",
      "추천용도": "근린생활",
      "연/대지면적": "722.22m2/509.1m2 (218.46평/153.99평)",
      "건축/전용면적": "283.25m2/-m2 (85.68평/-평)",
      "용적률/건폐율": "141.9%/55.6%",
      "지상/지하총층": "3층/B1층",
      "주실방향": "남향",
      "점포개수": "5개",
      "화장실개수": "3개",
      "총주차대수": "4대",
      "위반건축물 여부": "위반건축물 아님",
      "사용전력": "-",
      "사용승인일": "1977.11.17",
      "난방방식": "개별난방",
      "냉방시설": "-",
      "보안시설": "-",
      "기타시설": "-"
    },
    "추가_옵션": [],
    "주변_학교": [],
    "상세_설명": "* 준공업지역 및 성수IT 산업개발 진흥지구 내 위치함\n* 지상3층/지하1층으로 리모델링외 신축부지 용도\n* 꾸준한 성수1가 핫플 상권 확장으로 투자 메리트 높고 주변이 오피스 상권의 개발부지로 지식산업센터 및 사옥 신축 활발함\n* 현재 사무실외 공장으로 사용중으로 매도인 명도 조건임.\n* 명도기간은 매수인의 대출 여부 및 잔금일에 맞춰 협의 진행할 예정임.\n* 매도 가격은 매수 의향만 확실하면 협의 가능함."
  }
]